Metadata-Version: 2.1
Name: JSutils
Version: 0.2.1
Summary: Simple to use functions to emulate native functions like setInterval in JavaScript
Home-page: https://github.com/Jaimeloeuf/JSutils
Author: Jaime Loeuf
Author-email: jaimeloeuf@gmail.com
License: MIT
Download-URL: https://github.com/Jaimeloeuf/JSutils/archive/v0.2.0.tar.gz
Keywords: setInterval loop interval
Platform: UNKNOWN
Classifier: Development Status :: 4 - Beta
Classifier: Intended Audience :: Developers
Classifier: Environment :: Console
Classifier: License :: OSI Approved :: MIT License
Classifier: Natural Language :: English
Classifier: Programming Language :: Python :: 3.7
Classifier: Topic :: Utilities
